chatllm/__init__.py
chatllm/callbacks.py
chatllm/chatyuan.py
chatllm/closeai.py
chatllm/embedding.py
chatllm/_his/FaissANN.py
chatllm/_his/__init__.py
chatllm/_his/_chatllm.py
chatllm/_his/_qa.py
chatllm/aigc/__init__.py
chatllm/aigc/common.py
chatllm/api/TODO.md
chatllm/api/__init__.py
chatllm/api/app.py
chatllm/api/config.py
chatllm/api/datamodels.py
chatllm/api/openai_client.py
chatllm/api/sse_api.py
chatllm/api/test.py
chatllm/api/routes/__init__.py
chatllm/api/routes/api.py
chatllm/api/routes/base.py
chatllm/api/routes/completions.py
chatllm/api/routes/embeddings.py
chatllm/api/routes/responses.py
chatllm/applications/Question2Answer.py
chatllm/applications/__chatbase.py
chatllm/applications/__init__.py
chatllm/applications/chatann.py
chatllm/applications/chataudio.py
chatllm/applications/chatbase.py
chatllm/applications/chatcrawler.py
chatllm/applications/chatdoc.py
chatllm/applications/chatmind.py
chatllm/applications/chatpdf.py
chatllm/applications/chatsearch.py
chatllm/applications/chatweb.py
chatllm/applications/chatwhoosh.py
chatllm/applications/pipeline.py
chatllm/clis/README.md
chatllm/clis/__init__.py
chatllm/clis/cli.py
chatllm/langchain/TODO.md
chatllm/langchain/__init__.py
chatllm/langchain/chains.py
chatllm/langchain/datamodels.py
chatllm/langchain/demo.py
chatllm/langchain/llmcache.py
chatllm/langchain/缓存.py
chatllm/langchain/applications/__init__.py
chatllm/langchain/applications/_chatbase.py
chatllm/langchain/applications/chatbase.py
chatllm/langchain/callbacks/__init__.py
chatllm/langchain/callbacks/streaming.py
chatllm/langchain/chat_models/__init__.py
chatllm/langchain/chat_models/openai.py
chatllm/langchain/decorators/__init__.py
chatllm/langchain/decorators/common.py
chatllm/langchain/document_loaders/FilesLoader.py
chatllm/langchain/document_loaders/__init__.py
chatllm/langchain/document_loaders/pdf.py
chatllm/langchain/embeddings/OpenAIEmbeddings.py
chatllm/langchain/embeddings/__init__.py
chatllm/langchain/llms/ChatOpenAI.py
llm2openai-2023.7.19.18.52.8.dist-info/LICENSE
llm2openai-2023.7.19.18.52.8.dist-info/METADATA
llm2openai-2023.7.19.18.52.8.dist-info/WHEEL
llm2openai-2023.7.19.18.52.8.dist-info/entry_points.txt
llm2openai-2023.7.19.18.52.8.dist-info/top_level.txt
llm2openai-2023.7.19.18.52.8.dist-info/RECORD
